


{
    "id": 1,
    "type": "Versement",
    "note": "Versement pour la tontine de mars",
    "hours": "10 heures",
    "transactionDate": "2022-03-15T10:30:00Z",
    "user": {
      "id": 123,
      "infos":"suivi de toutes les infons du user"
    },
    "tontine": {
      "id": 456,
      "infons": "suivi de toutes les infos de la tontine sauf membersId et groups"
    },

    "transaction":[
      {
        "id":13,
        "amount":10000,
        "type":"Versement",
        "date":"2022-03-20",
        "time":"16:00",
        "group_id":2,
        "user_id":34
      },
      {
        "id":4,
        "amount":10000,
        "type":"Versement",
        "date":"2022-03-15",
        "time":"16:00",
        "group_id":27,
        "user_id":374
      },
      {
        "id":13,
        "amount":10000,
        "type":"Versement",
        "date":"2022-03-20",
        "time":"16:00",
        "group_id":2,
        "user_id":314
      },
      {
        "id":2,
        "amount":10000,
        "type":"Versement",
        "date":"2022-03-15",
        "time":"16:00",
        "group_id":552,
        "user_id":4
      },
      {
        "id":15,
        "amount":10000,
        "type":"Versement",
        "date":"2022-03-21",
        "time":"16:00",
        "group_id":12,
        "user_id":344
      },
      {
        "id":17,
        "amount":10000,
        "type":"Versement",
        "date":"2022-03-21",
        "time":"16:00",
        "group_id":21,
        "user_id":3
      }

    ],

    "transactonsByDate":[
      {
        "date":"2022-03-15",
        "transactions":[
          {
            "id":4,
            "amount":10000,
            "type":"Versement",
            "date":"2022-03-15",
            "time":"16:00",
            "group_id":27,
            "user_id":374
          },
          {
            "id":2,
            "amount":10000,
            "type":"Versement",
            "date":"2022-03-15",
            "time":"16:00",
            "group_id":552,
            "user_id":4
          }
        ]
      },
      {
        "date":"2022-03-20",
        "transactions":[
          {
            "id":13,
            "amount":10000,
            "type":"Versement",
            "date":"2022-03-20",
            "time":"16:00",
            "group_id":2,
            "user_id":34
          },
          {
            "id":13,
            "amount":10000,
            "type":"Versement",
            "date":"2022-03-20",
            "time":"16:00",
            "group_id":2,
            "user_id":314
          }
        ]
      },
      {
        "date":"2022-03-21",
        "transactions":[
          {
            "id":15,
            "amount":10000,
            "type":"Versement",
            "date":"2022-03-21",
            "time":"16:00",
            "group_id":12,
            "user_id":344
          },
          {
            "id":17,
            "amount":10000,
            "type":"Versement",
            "date":"2022-03-21",
            "time":"16:00",
            "group_id":21,
            "user_id":3
          }
        ]
      }
    ]
  }












  'versement',
              


              'Reception',
              color: ,

              'Retrait',
              color: ,


 

  